env_mcp_test_sample/__init__.py
env_mcp_test_sample/env_mcp_test_sample.py
env_mcp_test_sample/tools/get_jira_ticket_status_tool.py
env_mcp_test_sample-0.1.0.dist-info/METADATA
env_mcp_test_sample-0.1.0.dist-info/WHEEL
env_mcp_test_sample-0.1.0.dist-info/entry_points.txt
env_mcp_test_sample-0.1.0.dist-info/RECORD
