Metadata-Version: 2.4
Name: env-mcp-test-sample
Version: 0.1.0
Summary: Add your description here
Requires-Python: >=3.12
Requires-Dist: build>=1.2.2.post1
Requires-Dist: mcp[cli]>=1.12.2
Requires-Dist: requests>=2.32.4
Requires-Dist: twine>=6.1.0
